{"particles":{"number":{"value":200,"density":{"enable":true,"value_area":1200}},"color":{"value":["#FF5733","#FFBD33","#33FF57","#339CFF","#FF33E9"]},"shape":{"type":["circle","triangle","polygon"],"stroke":{"width":0,"color":"#000000"},"polygon":{"nb_sides":5}},"size":{"value":10,"random":true,"anim":{"enable":false,"speed":20,"size_min":0.1,"sync":false}},"line_linked":{"enable":false},"move":{"enable":true,"speed":2,"direction":"bottom","random":true,"straight":false,"out_mode":"out","bounce":false,"attract":{"enable":true,"rotateX":600,"rotateY":1200}}},"interactivity":{"detect_on":"canvas","events":{"onhover":{"enable":true,"mode":"repulse","distance":100},"onclick":{"enable":true,"mode":"push"},"resize":true},"modes":{"bubble":{"distance":400,"duration":2,"size":0,"opacity":8}}},"retina_detect":true}